{
	"name": "UseCase3",
	"properties": {
		"activities": [
			{
				"name": "Copy data from blob to database",
				"type": "Copy",
				"dependsOn": [
					{
						"activity": "Start time",
						"dependencyConditions": [
							"Succeeded"
						]
					}
				],
				"policy": {
					"timeout": "0.12:00:00",
					"retry": 0,
					"retryIntervalInSeconds": 30,
					"secureOutput": false,
					"secureInput": false
				},
				"userProperties": [],
				"typeProperties": {
					"source": {
						"type": "DelimitedTextSource",
						"storeSettings": {
							"type": "AzureBlobStorageReadSettings",
							"recursive": true,
							"modifiedDatetimeStart": "2025-07-13T15:07:00.000Z",
							"wildcardFileName": "*",
							"enablePartitionDiscovery": false
						},
						"formatSettings": {
							"type": "DelimitedTextReadSettings"
						}
					},
					"sink": {
						"type": "AzureSqlSink",
						"writeBehavior": "insert",
						"sqlWriterUseTableLock": false
					},
					"enableStaging": false,
					"translator": {
						"type": "TabularTranslator",
						"typeConversion": true,
						"typeConversionSettings": {
							"allowDataTruncation": true,
							"treatBooleanAsNumber": false
						}
					}
				},
				"inputs": [
					{
						"referenceName": "DelimitedText13",
						"type": "DatasetReference"
					}
				],
				"outputs": [
					{
						"referenceName": "AzureSqlTable1",
						"type": "DatasetReference"
					}
				]
			},
			{
				"name": "Start time",
				"type": "SetVariable",
				"dependsOn": [],
				"policy": {
					"secureOutput": false,
					"secureInput": false
				},
				"userProperties": [],
				"typeProperties": {
					"variableName": "status",
					"value": {
						"value": "@utcNow()",
						"type": "Expression"
					}
				}
			},
			{
				"name": "End time",
				"type": "SetVariable",
				"dependsOn": [
					{
						"activity": "Copy data from blob to database",
						"dependencyConditions": [
							"Succeeded"
						]
					}
				],
				"policy": {
					"secureOutput": false,
					"secureInput": false
				},
				"userProperties": [],
				"typeProperties": {
					"variableName": "status",
					"value": {
						"value": "@utcNow()",
						"type": "Expression"
					}
				}
			}
		],
		"variables": {
			"status": {
				"type": "String"
			}
		},
		"annotations": []
	}
}